{
  "required": true,
  "minVersion": "0.8",
  "package": "si.bismuth.stats.mixins",
  "compatibilityLevel": "JAVA_8",
  "mixins": [
    "DistanceFormatterMixin",
    "DivideByTenFormatterMixin",
    "NumberFormatterMixin",
    "PlayerStatsMixin",
    "ServerPlayerEntityMixin",
    "ServerPlayerStatsMixin",
    "StatCounterMixin",
    "StatMixin",
    "TimeFormatterMixin"
  ],
  "client": [
    "CraftPlanksTutorialStepMixin",
    "FindTreeTutorialStepMixin",
    "StatsScreen.AbstractStatsListWidgetMixin",
    "StatsScreen.EntityStatsListWidgetMixin",
    "StatsScreen.GeneralStatsListWidgetMixin",
    "StatsScreen.ItemStatsListWidgetMixin",
    "StatsScreen.ItemStatsListWidgetStatComparatorMixin",
    "StatsScreen.StatsListWidgetMixin",
    "StatsScreen.StatsListWidgetStatComparatorMixin"
  ],
  "server": [
  ]
}
